{"name":"maven使用指南","tagline":"tell you ,how to use maven!","body":"\r\n#maven使用指南\r\n\r\n\r\n\r\n\r\n\r\n**为什么要写maven？**\r\n\r\nmaven作为目前最为流行的项目框架构建工具，有着不可替代的作用，在较大的公司，使用maven是一个必不可少的技能 ，所以，本教程站在入门读者的角度，从入门开始一步一步的详细介绍maven，希望能对又需要的同学有帮助。\r\n\r\n- **作者**：JA\r\n- **授权**：[署名-非商用许可证](http://creativecommons.org/licenses/by-nc/4.0/)\r\n- **联系邮箱**： <message0203@gmail.com>\r\n\r\n#目录\r\n\r\n第1章 maven概览及快速入门\r\n\r\n第2章 Windows 和 Eclipse的配置\r\n\r\n第3章 一切基于pom\r\n\r\n第4章 maven依赖特性\r\n\r\n第5章 maven继承特性\r\n\r\n第6章 maven聚合特性\r\n\r\n第7章 仓库\r\n\r\n第8章 私服nexus\r\n\r\n第9章 maven的插件和生命周期\r\n\r\n第10章 多环境下构建项目\r\n\r\n第11章 使用maven+svn+jenkins持续集成项目\r\n\r\n\r\n","google":"","note":"Don't delete this file! It's used internally to help with page regeneration."}